chips/__init__.py
chips/__main__.py
chips/commands/add.py
chips/commands/remove.py
chips/commands/results.py
chips/commands/setup.py
chips/common/__init__.py
chips/common/basic_excludes.py
chips/common/messages_service.py
chips/services/__init__.py
chips/services/chipper.py
chips/services/main.py
python_chips-1.0.15.dist-info/WHEEL
python_chips-1.0.15.dist-info/METADATA
python_chips-1.0.15.dist-info/RECORD
