Metadata-Version: 2.1
Name: python-chips
Version: 1.0.15
Summary: A tool that inserts "chips" to your code, detecting unused fragments. Might be used for developing, refactoring and manual testing purposes
Author: Ruslan Kovalchuk
Author-email: russkovalchuk@gmail.com
Requires-Python: >=3.7
Classifier: Programming Language :: Python :: 3
Classifier: Programming Language :: Python :: 3.10
Classifier: Programming Language :: Python :: 3.7
Classifier: Programming Language :: Python :: 3.8
Classifier: Programming Language :: Python :: 3.9
Provides-Extra: runtime
Requires-Dist: ast2json (>=0.3,<0.4)
Requires-Dist: colorama (>=0.4.4,<0.5.0)
Requires-Dist: gitignore-parser (>=0.0.8,<0.0.9)
Requires-Dist: prettytable (>=3.3.0,<4.0.0)
